Week 2/Full Adder/Codes.v
module full_adder (
    input A,
    input B,
    input Cin,
    output S,
    output Cout
);

    
    assign S = A ^ B ^ Cin;

    
    assign Cout = (A & B) | (B & Cin) | (A & Cin);

endmodule

Week 2/Full Adder/TestBench.v
`timescale 1ns / 1ps

module tb_full_adder;

    
    reg A;
    reg B;
    reg Cin;

    
    wire S;
    wire Cout;

    
    full_adder uut (
        .A(A),
        .B(B),
        .Cin(Cin),
        .S(S),
        .Cout(Cout)
    );

    
    initial begin
        $dumpfile("full_adder.vcd");
        $dumpvars(0, tb_full_adder);
    end

  
    initial begin
        #10 A = 1'b0; B = 1'b0; Cin = 1'b0;
        #10 A = 1'b0; B = 1'b0; Cin = 1'b1;
        #10 A = 1'b0; B = 1'b1; Cin = 1'b0;
        #10 A = 1'b0; B = 1'b1; Cin = 1'b1;
        #10 A = 1'b1; B = 1'b0; Cin = 1'b0;
        #10 A = 1'b1; B = 1'b0; Cin = 1'b1;
        #10 A = 1'b1; B = 1'b1; Cin = 1'b0;
        #10 A = 1'b1; B = 1'b1; Cin = 1'b1;
        #10 $finish;
    end

endmodule

Week 2/Full Adder/full_adder.vcd
$date
	Wed Aug 20 16:49:16 2025
$end
$version
	Icarus Verilog
$end
$timescale
	1ps
$end
$scope module tb_full_adder $end
$var wire 1 ! S $end
$var wire 1 " Cout $end
$var reg 1 # A $end
$var reg 1 $ B $end
$var reg 1 % Cin $end
$scope module uut $end
$var wire 1 # A $end
$var wire 1 $ B $end
$var wire 1 % Cin $end
$var wire 1 " Cout $end
$var wire 1 ! S $end
$upscope $end
$upscope $end
$enddefinitions $end
$comment Show the parameter values. $end
$dumpall
$end
#0
$dumpvars
x%
x$
x#
x"
x!
$end
#10000
0"
0!
0%
0$
0#
#20000
1!
1%
#30000
0%
1$
#40000
1"
0!
1%
#50000
0"
1!
0%
0$
1#
#60000
1"
0!
1%
#70000
0%
1$
#80000
1!
1%
