Week 1/Boolean Function/bool_func.v
module boolean_function_dataflow (
    input  A,
    input  B,
    input  C,
    output F
);

    assign F = (A | C) & (A | ~B) & (~B | C);

endmodule

Week 1/Boolean Function/bool_func_testbench.v
`timescale 1ns / 1ps

module testbench_dataflow;

    reg A, B, C;
    wire F;

    boolean_function_dataflow dut (
        .A(A),
        .B(B),
        .C(C),
        .F(F)
    );

    initial begin
        $dumpfile("waveform.vcd");
        $dumpvars(0, testbench_dataflow);

        $monitor("Time(ns) | A | B | C | F");
        $monitor("--------------------------");

        #10; A = 0; B = 0; C = 0;
        #10; A = 0; B = 0; C = 1;
        #10; A = 0; B = 1; C = 0;
        #10; A = 0; B = 1; C = 1;
        #10; A = 1; B = 0; C = 0;
        #10; A = 1; B = 0; C = 1;
        #10; A = 1; B = 1; C = 0;
        #10; A = 1; B = 1; C = 1;

        #10;
        $finish;
    end

endmodule

Week 1/waveform.vcd
$date
	Sun Aug 17 09:35:25 2025
$end
$version
	Icarus Verilog
$end
$timescale
	1ps
$end
$scope module testbench_dataflow $end
$var wire 1 ! F $end
$var reg 1 " A $end
$var reg 1 # B $end
$var reg 1 $ C $end
$scope module dut $end
$var wire 1 " A $end
$var wire 1 # B $end
$var wire 1 $ C $end
$var wire 1 ! F $end
$upscope $end
$upscope $end
$enddefinitions $end
$comment Show the parameter values. $end
$dumpall
$end
#0
$dumpvars
x$
x#
x"
x!
$end
#10000
0!
0$
0#
0"
#20000
1!
1$
#30000
0!
0$
1#
#40000
1$
#50000
1!
0$
0#
1"
#60000
1$
#70000
0!
0$
1#
#80000
1!
1$
